dddroller/__init__.py
dddroller/__main__.py
dddroller/class_roller.py
dddroller/funtion_roller.py
dddroller/parser.py
dddroller/utilities.py
dddroller-1.1.0.dist-info/WHEEL
dddroller-1.1.0.dist-info/METADATA
dddroller-1.1.0.dist-info/RECORD
